LICENSE
README.md
setup.py
tripayiin/__init__.py
tripayiin/api.py
tripayiin/exception.py
tripayiin/py.typed
tripayiin.egg-info/PKG-INFO
tripayiin.egg-info/SOURCES.txt
tripayiin.egg-info/dependency_links.txt
tripayiin.egg-info/not-zip-safe
tripayiin.egg-info/requires.txt
tripayiin.egg-info/top_level.txt
tripayiin/method/__init__.py
tripayiin/method/merchant/__init__.py
tripayiin/method/merchant/costCalculator.py
tripayiin/method/merchant/paymentChannel.py
tripayiin/method/merchant/transactionList.py
tripayiin/method/payment/__init__.py
tripayiin/method/payment/intruction.py
tripayiin/method/transaction/__init__.py
tripayiin/method/transaction/closedPayment/__init__.py
tripayiin/method/transaction/closedPayment/createPayment.py
tripayiin/method/transaction/closedPayment/detailPayment.py
tripayiin/method/transaction/closedPayment/statusPayment.py
tripayiin/method/transaction/openPayment/__init__.py
tripayiin/method/transaction/openPayment/createPayment.py
tripayiin/method/transaction/openPayment/detailPayment.py
tripayiin/types/__init__.py
tripayiin/types/code.py
tripayiin/types/orderItem.py
tripayiin/types/response.py